[
  {
    "url": "https://www.margaretgreenanimalrescue.org.uk/dog/56198/",
    "name": "Lottie",
    "breed": "Springer Spaniel Cross",
    "age": "0 years",
    "sex": "Female",
    "location": "Margaret Green (Wareham, Dorset)",
    "distance_miles": 49.7,
    "source": "Margaret Green",
    "reserved": false,
    "first_seen": "2026-07-23T14:27:19.782768+00:00"
  },
  {
    "url": "https://www.manytearsrescue.org/adopt/dogs/6016/",
    "name": "Judy",
    "breed": "Cocker Spaniel",
    "age": "7 years",
    "sex": "Female",
    "location": "Many Tears (Many Tears,  Llanelli,  Carmarthenshire; UK-wide fosters)",
    "distance_miles": 150.3,
    "source": "Many Tears",
    "reserved": false,
    "first_seen": "2026-07-23T10:01:11.413311+00:00"
  },
  {
    "url": "https://prodogsdirect.org.uk/mora-working-cocker-spaniel/",
    "name": "Mora",
    "breed": "Cocker Spaniel",
    "age": null,
    "sex": null,
    "location": "Pro Dogs Direct (Surrey)",
    "distance_miles": 32.3,
    "source": "Pro Dogs Direct",
    "reserved": false,
    "first_seen": "2026-07-22T19:51:31.582244+00:00"
  },
  {
    "url": "https://teckelsanimalsanctuaries.co.uk/animals/hetty/",
    "name": "Hetty",
    "breed": "Cocker Spaniel",
    "age": "8 years",
    "sex": "Female",
    "location": "Teckels Animal Sanctuary (Whitminster, Glos)",
    "distance_miles": 90.0,
    "source": "Teckels Animal Sanctuary",
    "reserved": false,
    "first_seen": "2026-07-22T16:44:21.892185+00:00"
  },
  {
    "url": "https://www.rspca-isleofwight.org.uk/pet/star/",
    "name": "Star",
    "breed": "Border Collie Crossbreed",
    "age": "5 months",
    "sex": "Female",
    "location": "RSPCA Isle of Wight (Godshill, IoW)",
    "distance_miles": 15.6,
    "source": "RSPCA Isle of Wight",
    "reserved": false,
    "first_seen": "2026-07-22T15:33:54.826099+00:00"
  },
  {
    "url": "https://www.lastchanceanimalrescue.co.uk/kennel/dog.php#Copper",
    "name": "Copper",
    "breed": "King Charles Spaniel",
    "age": "5 years",
    "sex": "Male",
    "location": "Last Chance Edenbridge",
    "distance_miles": 53.5,
    "source": "Last Chance",
    "reserved": false,
    "first_seen": "2026-07-22T15:33:54.826099+00:00"
  },
  {
    "url": "https://www.dogstrust.org.uk/rehoming/dogs/spaniel-english-springer/3652880",
    "name": "Whistle",
    "breed": "Spaniel (English Springer) Cross",
    "age": "4y 5m",
    "sex": "Male",
    "location": "Dogs Trust Shoreham (Sussex)",
    "distance_miles": 31.3,
    "source": "Dogs Trust",
    "reserved": true,
    "first_seen": "2026-07-22T15:33:54.826099+00:00"
  },
  {
    "url": "https://www.margaretgreenanimalrescue.org.uk/dog/54896/",
    "name": "Flossie",
    "breed": "Collie x",
    "age": "6 years",
    "sex": "Female",
    "location": "Margaret Green (Wareham, Dorset)",
    "distance_miles": 49.7,
    "source": "Margaret Green",
    "reserved": false,
    "first_seen": "2026-07-22T14:07:00.404101+00:00"
  },
  {
    "url": "https://www.pawprints2freedom.co.uk/post/fred-1-year-old-male",
    "name": "Fred",
    "breed": "border collie to shame! Freds current famil",
    "age": "1 years",
    "sex": "Male",
    "location": "Pawprints to Freedom (UK-wide fosters)",
    "distance_miles": 107.1,
    "source": "Pawprints to Freedom",
    "reserved": false,
    "first_seen": "2026-07-22T12:44:43.553189+00:00"
  },
  {
    "url": "https://www.manytearsrescue.org/adopt/dogs/6022/",
    "name": "Pop",
    "breed": "Collie x Jack Russell Terrier",
    "age": "1 year",
    "sex": "Female",
    "location": "Many Tears (Many Tears,  Llanelli,  Carmarthenshire; UK-wide fosters)",
    "distance_miles": 150.3,
    "source": "Many Tears",
    "reserved": false,
    "first_seen": "2026-07-22T12:07:12.673552+00:00"
  },
  {
    "url": "https://www.battersea.org.uk/dogs/dog-rehoming-gallery/chilli",
    "name": "Chilli",
    "breed": "Spaniel: Tibetan",
    "age": "5 Years",
    "sex": null,
    "location": "Battersea London",
    "distance_miles": 60.4,
    "source": "Battersea",
    "reserved": false,
    "first_seen": "2026-07-22T08:42:05.014768+00:00"
  },
  {
    "url": "https://alldogsmatter.co.uk/dogs/jasper-4/",
    "name": "Jasper",
    "breed": "Collie Cross",
    "age": "2 years approx",
    "sex": "Male",
    "location": "AllDogsMatter (Waltham Abbey)",
    "distance_miles": 66.1,
    "source": "AllDogsMatter",
    "reserved": false,
    "first_seen": "2026-07-21T15:02:30.267129+00:00"
  },
  {
    "url": "https://prodogsdirect.org.uk/ivy-ckc-spaniel/",
    "name": "Ivy",
    "breed": "Spaniel",
    "age": null,
    "sex": null,
    "location": "Pro Dogs Direct (Surrey)",
    "distance_miles": 32.3,
    "source": "Pro Dogs Direct",
    "reserved": false,
    "first_seen": "2026-07-21T12:11:52.122214+00:00"
  },
  {
    "url": "https://heathlands.org.uk/dog.php?id=867",
    "name": "Isla & Scarlett",
    "breed": "Border Collies",
    "age": "11 & 13 years",
    "sex": null,
    "location": "Heathlands Animal Sanctuary (Royston, Herts)",
    "distance_miles": 96.9,
    "source": "Heathlands Animal Sanctuary",
    "reserved": false,
    "first_seen": "2026-07-19T19:42:03.297148+00:00"
  },
  {
    "url": "https://www.manytearsrescue.org/adopt/dogs/5997/",
    "name": "Ureka",
    "breed": "Cocker Spaniel",
    "age": "1 year",
    "sex": "Female",
    "location": "Many Tears (Many Tears,  Llanelli,  Carmarthenshire; UK-wide fosters)",
    "distance_miles": 150.3,
    "source": "Many Tears",
    "reserved": false,
    "first_seen": "2026-07-18T13:44:38.469176+00:00"
  },
  {
    "url": "https://www.manytearsrescue.org/adopt/dogs/5963/",
    "name": "Dianna",
    "breed": "Cocker Spaniel",
    "age": "5 years",
    "sex": "Female",
    "location": "Many Tears (Many Tears,  Llanelli,  Carmarthenshire; UK-wide fosters)",
    "distance_miles": 150.3,
    "source": "Many Tears",
    "reserved": false,
    "first_seen": "2026-07-18T11:02:00.807491+00:00"
  },
  {
    "url": "https://www.lastchanceanimalrescue.co.uk/kennel/dog.php#Kovu",
    "name": "Kovu",
    "breed": "Spaniel cross",
    "age": "2yrs",
    "sex": "Male",
    "location": "Last Chance Edenbridge",
    "distance_miles": 53.5,
    "source": "Last Chance",
    "reserved": false,
    "first_seen": "2026-07-17T14:00:49.498806+00:00"
  },
  {
    "url": "https://www.manytearsrescue.org/adopt/dogs/5962/",
    "name": "Dory",
    "breed": "Cocker Spaniel",
    "age": "4 years",
    "sex": "Female",
    "location": "Many Tears (Many Tears,  Llanelli,  Carmarthenshire; UK-wide fosters)",
    "distance_miles": 150.3,
    "source": "Many Tears",
    "reserved": false,
    "first_seen": "2026-07-17T12:08:17.606895+00:00"
  },
  {
    "url": "https://prodogsdirect.org.uk/fern-ckc-spaniel/",
    "name": "Fern",
    "breed": "Spaniel",
    "age": null,
    "sex": null,
    "location": "Pro Dogs Direct (Surrey)",
    "distance_miles": 32.3,
    "source": "Pro Dogs Direct",
    "reserved": false,
    "first_seen": "2026-07-17T10:55:18.773762+00:00"
  },
  {
    "url": "https://www.manytearsrescue.org/adopt/dogs/5965/",
    "name": "Demi",
    "breed": "Cocker Spaniel",
    "age": "4 years",
    "sex": "Female",
    "location": "Many Tears (Many Tears,  Llanelli,  Carmarthenshire; UK-wide fosters)",
    "distance_miles": 150.3,
    "source": "Many Tears",
    "reserved": false,
    "first_seen": "2026-07-17T10:55:18.773762+00:00"
  },
  {
    "url": "https://www.manytearsrescue.org/adopt/dogs/5976/",
    "name": "Dolly",
    "breed": "Cocker Spaniel",
    "age": "6 years",
    "sex": "Female",
    "location": "Many Tears (Many Tears,  Llanelli,  Carmarthenshire; UK-wide fosters)",
    "distance_miles": 150.3,
    "source": "Many Tears",
    "reserved": false,
    "first_seen": "2026-07-17T10:55:18.773762+00:00"
  },
  {
    "url": "https://www.manytearsrescue.org/adopt/dogs/5972/",
    "name": "Danny",
    "breed": "American Cocker Spaniel",
    "age": "4 years",
    "sex": "Male",
    "location": "Many Tears (Many Tears,  Llanelli,  Carmarthenshire; UK-wide fosters)",
    "distance_miles": 150.3,
    "source": "Many Tears",
    "reserved": false,
    "first_seen": "2026-07-16T23:41:58.482795+00:00"
  },
  {
    "url": "https://teckelsanimalsanctuaries.co.uk/animals/harriet/",
    "name": "Harriet",
    "breed": "Cocker Spaniel",
    "age": "9 years",
    "sex": "Female",
    "location": "Teckels Animal Sanctuary (Whitminster, Glos)",
    "distance_miles": 90.0,
    "source": "Teckels Animal Sanctuary",
    "reserved": false,
    "first_seen": "2026-07-14T15:10:47.487084+00:00"
  },
  {
    "url": "https://www.dogstrust.org.uk/rehoming/dogs/spaniel-english-springer/3642526",
    "name": "Sadie",
    "breed": "Spaniel (English Springer)",
    "age": "4y 9m",
    "sex": "Female",
    "location": "Dogs Trust Newbury (Berkshire)",
    "distance_miles": 45.3,
    "source": "Dogs Trust",
    "reserved": false,
    "first_seen": "2026-07-14T11:53:20.071857+00:00"
  },
  {
    "url": "https://alldogsmatter.co.uk/dogs/bear/",
    "name": "Bear",
    "breed": "Spaniel",
    "age": "10 Months",
    "sex": "Male",
    "location": "AllDogsMatter (London N2)",
    "distance_miles": 66.1,
    "source": "AllDogsMatter",
    "reserved": false,
    "first_seen": "2026-07-13T16:05:21.463052+00:00"
  },
  {
    "url": "https://woodgreen.org.uk/pets/figgy-crossbreed-dog/",
    "name": "Figgy",
    "breed": "Border Collie",
    "age": "1 year",
    "sex": "Female",
    "location": "Woodgreen Pets Charity (Godmanchester, Cambs)",
    "distance_miles": 110.5,
    "source": "Woodgreen Pets Charity",
    "reserved": false,
    "first_seen": "2026-07-13T16:05:21.463052+00:00"
  },
  {
    "url": "https://www.englishspringerrescue.co.uk/bella-4/",
    "name": "Bella",
    "breed": "English Springer Spaniel",
    "age": null,
    "sex": null,
    "location": "NWESSR (North West England)",
    "distance_miles": 183.0,
    "source": "NWESSR",
    "reserved": false,
    "first_seen": "2026-07-12T14:12:35.025419+00:00"
  },
  {
    "url": "https://www.englishspringerrescue.co.uk/emily/",
    "name": "Emily",
    "breed": "English Springer Spaniel",
    "age": null,
    "sex": null,
    "location": "NWESSR (North West England)",
    "distance_miles": 183.0,
    "source": "NWESSR",
    "reserved": false,
    "first_seen": "2026-07-11T01:12:14.843799+00:00"
  },
  {
    "url": "https://www.manytearsrescue.org/adopt/dogs/5958/",
    "name": "Berry",
    "breed": "Cocker Spaniel",
    "age": "7 years",
    "sex": "Female",
    "location": "Many Tears (Many Tears,  Llanelli,  Carmarthenshire; UK-wide fosters)",
    "distance_miles": 150.3,
    "source": "Many Tears",
    "reserved": false,
    "first_seen": "2026-07-10T23:41:45.046632+00:00"
  },
  {
    "url": "https://www.englishspringerrescue.co.uk/bear/",
    "name": "Bear",
    "breed": "English Springer Spaniel",
    "age": null,
    "sex": null,
    "location": "NWESSR (North West England)",
    "distance_miles": 183.0,
    "source": "NWESSR",
    "reserved": false,
    "first_seen": "2026-07-10T17:46:32.191843+00:00"
  },
  {
    "url": "https://www.englishspringerrescue.co.uk/mylo/",
    "name": "Mylo",
    "breed": "English Springer Spaniel",
    "age": null,
    "sex": null,
    "location": "NWESSR (North West England)",
    "distance_miles": 183.0,
    "source": "NWESSR",
    "reserved": false,
    "first_seen": "2026-07-10T17:46:32.191843+00:00"
  },
  {
    "url": "https://www.spanielrescuefoundation.org/srf156",
    "name": "Cracker",
    "breed": "Working Cocker Spaniel",
    "age": null,
    "sex": null,
    "location": "Spaniel Rescue Foundation (Middle Rasen, Lincs; UK-wide fosters)",
    "distance_miles": 182.8,
    "source": "Spaniel Rescue Foundation",
    "reserved": false,
    "first_seen": "2026-07-09T21:52:01.989009+00:00"
  },
  {
    "url": "https://www.englishspringerrescue.co.uk/murphy-6/",
    "name": "Murphy",
    "breed": "English Springer Spaniel",
    "age": null,
    "sex": null,
    "location": "NWESSR (North West England)",
    "distance_miles": 183.0,
    "source": "NWESSR",
    "reserved": false,
    "first_seen": "2026-07-08T03:40:54.418121+00:00"
  },
  {
    "url": "https://www.englishspringerrescue.co.uk/sam/",
    "name": "Sam",
    "breed": "English Springer Spaniel",
    "age": null,
    "sex": null,
    "location": "NWESSR (North West England)",
    "distance_miles": 183.0,
    "source": "NWESSR",
    "reserved": false,
    "first_seen": "2026-07-08T03:40:54.418121+00:00"
  },
  {
    "url": "https://woodgreen.org.uk/pets/ci-ci-springer-spaniel-cross-dog/",
    "name": "Ci Ci",
    "breed": "springer spaniel cross",
    "age": "2 years",
    "sex": "Female",
    "location": "Woodgreen Pets Charity (Godmanchester, Cambs)",
    "distance_miles": 110.5,
    "source": "Woodgreen Pets Charity",
    "reserved": false,
    "first_seen": "2026-07-03T15:28:05.691348+00:00"
  },
  {
    "url": "https://woodgreen.org.uk/pets/max-collie-border-x-lurcher-dog/",
    "name": "Max",
    "breed": "collie",
    "age": "7 years",
    "sex": "Male",
    "location": "Woodgreen Pets Charity (Godmanchester, Cambs)",
    "distance_miles": 110.5,
    "source": "Woodgreen Pets Charity",
    "reserved": false,
    "first_seen": "2026-07-03T08:29:34.862716+00:00"
  },
  {
    "url": "https://www.spanielrescuefoundation.org/srf162",
    "name": "Brodie",
    "breed": "Sprocker",
    "age": null,
    "sex": null,
    "location": "Spaniel Rescue Foundation (Middle Rasen, Lincs; UK-wide fosters)",
    "distance_miles": 182.8,
    "source": "Spaniel Rescue Foundation",
    "reserved": false,
    "first_seen": "2026-07-01T18:28:52.952814+00:00"
  },
  {
    "url": "https://www.spanielrescuefoundation.org/srf149",
    "name": "Ralph",
    "breed": "Cocker spaniel (chocolate)",
    "age": null,
    "sex": null,
    "location": "Spaniel Rescue Foundation (Middle Rasen, Lincs; UK-wide fosters)",
    "distance_miles": 182.8,
    "source": "Spaniel Rescue Foundation",
    "reserved": false,
    "first_seen": "2026-07-01T18:28:52.952814+00:00"
  },
  {
    "url": "https://www.protectingprelovedbordercollies.org.uk/dogs-for-rehoming#lottie",
    "name": "Lottie",
    "breed": "Border Collie (rescue specialist)",
    "age": "5 years",
    "sex": null,
    "location": "PPBC (Ammanford, Wales; UK-wide fosters)",
    "distance_miles": 147.3,
    "source": "PPBC",
    "reserved": false,
    "first_seen": "2026-07-01T09:49:45.315281+00:00"
  },
  {
    "url": "https://www.helpinghoundshampshire.com/dog-information/nessie",
    "name": "Nessie",
    "breed": "White/black springer spaniel cross",
    "age": "7 months",
    "sex": "Female",
    "location": "Helping Hounds (Grayshott, Surrey/Hants)",
    "distance_miles": 25.3,
    "source": "Helping Hounds",
    "reserved": false,
    "first_seen": "2026-06-28T19:06:30.883189+00:00"
  },
  {
    "url": "https://www.dogstrust.org.uk/rehoming/dogs/chihuahua-long-coat/3644634",
    "name": "Lucy",
    "breed": "Chihuahua (Long Coat) Cross \u00d7 Collie (Border)",
    "age": "11y 6m",
    "sex": "Female",
    "location": "Dogs Trust Newbury (Berkshire)",
    "distance_miles": 45.3,
    "source": "Dogs Trust",
    "reserved": false,
    "first_seen": "2026-06-27T12:14:27.892177+00:00"
  },
  {
    "url": "https://themayhew.org/dogs/alfie-moon/",
    "name": "Alfie Moon",
    "breed": "Cocker Spaniel x Poodle Meet Alfie Moon",
    "age": "3 years 1 months old",
    "sex": null,
    "location": "Mayhew (London NW10)",
    "distance_miles": 62.1,
    "source": "Mayhew",
    "reserved": true,
    "first_seen": "2026-06-24T16:53:28.492980+00:00"
  },
  {
    "url": "https://prodogsdirect.org.uk/angel-ckc-spaniel/",
    "name": "Angel",
    "breed": "Spaniel",
    "age": null,
    "sex": null,
    "location": "Pro Dogs Direct (Surrey)",
    "distance_miles": 32.3,
    "source": "Pro Dogs Direct",
    "reserved": false,
    "first_seen": "2026-06-22T21:03:52.520621+00:00"
  },
  {
    "url": "https://spanielaid.co.uk/spaniel/fred-sa4729-foster-view-to-adopt/",
    "name": "Fred",
    "breed": "Sprocker",
    "age": null,
    "sex": "Male",
    "location": "Basingstoke, Hampshire, England",
    "distance_miles": 25.2,
    "source": "Spaniel Aid",
    "reserved": true,
    "first_seen": "2026-06-20T15:36:34.541207+00:00"
  },
  {
    "url": "https://www.manytearsrescue.org/adopt/dogs/5934/",
    "name": "Whispy",
    "breed": "Cocker Spaniel",
    "age": "7 years",
    "sex": "Female",
    "location": "Many Tears (Many Tears,  Llanelli,  Carmarthenshire; UK-wide fosters)",
    "distance_miles": 150.3,
    "source": "Many Tears",
    "reserved": false,
    "first_seen": "2026-06-19T12:54:31.413738+00:00"
  },
  {
    "url": "https://prodogsdirect.org.uk/harper-cocker-spaniel/",
    "name": "Harper",
    "breed": "Cocker Spaniel",
    "age": null,
    "sex": null,
    "location": "Pro Dogs Direct (Kent)",
    "distance_miles": 32.3,
    "source": "Pro Dogs Direct",
    "reserved": false,
    "first_seen": "2026-06-18T21:27:15.068164+00:00"
  },
  {
    "url": "https://www.syessr.org.uk/items/sonny",
    "name": "Sonny",
    "breed": "Collie/Springer match",
    "age": "Approx 4 years",
    "sex": null,
    "location": "SYESSR (Sheffield, South Yorkshire)",
    "distance_miles": 219.6,
    "source": "SYESSR",
    "reserved": false,
    "first_seen": "2026-06-17T18:39:06.590145+00:00"
  },
  {
    "url": "https://spanielaid.co.uk/spaniel/spencer-sa4844/",
    "name": "Spencer",
    "breed": "- Spaniel Aid CIO",
    "age": null,
    "sex": null,
    "location": "Spaniel Aid foster (UK)",
    "distance_miles": null,
    "source": "Spaniel Aid",
    "reserved": true,
    "first_seen": "2026-06-09T20:52:03.951394+00:00"
  },
  {
    "url": "https://www.dogsblog.com/margot-17/",
    "name": "Margot",
    "breed": "Collie Cross",
    "age": "1-2 years",
    "sex": "Female",
    "location": "In Yorkshirehumberside",
    "distance_miles": null,
    "source": "Dogsblog",
    "reserved": false,
    "first_seen": "2026-06-09T10:17:29.124426+00:00"
  },
  {
    "url": "https://www.englishspringerrescue.co.uk/millie-4/",
    "name": "Millie",
    "breed": "English Springer Spaniel",
    "age": null,
    "sex": null,
    "location": "NWESSR (North West England)",
    "distance_miles": 183.0,
    "source": "NWESSR",
    "reserved": false,
    "first_seen": "2026-06-08T12:16:41.903704+00:00"
  },
  {
    "url": "https://www.dogsblog.com/lilly-109/",
    "name": "Lilly",
    "breed": "Collie Cross",
    "age": "6+ years",
    "sex": "Female",
    "location": "South East England",
    "distance_miles": null,
    "source": "Dogsblog",
    "reserved": false,
    "first_seen": "2026-06-08T10:38:49.822535+00:00"
  },
  {
    "url": "https://www.englishspringerrescue.co.uk/molly-8/",
    "name": "Molly",
    "breed": "English Springer Spaniel",
    "age": null,
    "sex": null,
    "location": "NWESSR (North West England)",
    "distance_miles": 183.0,
    "source": "NWESSR",
    "reserved": false,
    "first_seen": "2026-06-07T15:33:14.698225+00:00"
  },
  {
    "url": "https://furbuddies.org/remy",
    "name": "Remy",
    "breed": "Collie",
    "age": null,
    "sex": "Male",
    "location": "FurBuddies (Hordle, New Forest)",
    "distance_miles": 28.0,
    "source": "FurBuddies",
    "reserved": false,
    "first_seen": "2026-06-05T15:30:05.439958+00:00"
  },
  {
    "url": "https://www.dogstrust.org.uk/rehoming/dogs/collie-border/3639862",
    "name": "Max",
    "breed": "Collie (Border) Cross",
    "age": "2y 10m",
    "sex": "Male",
    "location": "Dogs Trust Salisbury (Wiltshire)",
    "distance_miles": 40.5,
    "source": "Dogs Trust",
    "reserved": false,
    "first_seen": "2026-06-04T12:24:06.246414+00:00"
  },
  {
    "url": "https://www.manytearsrescue.org/adopt/dogs/5881/",
    "name": "Daisy",
    "breed": "Cocker Spaniel",
    "age": "4 years",
    "sex": "Female",
    "location": "Many Tears (Many Tears,  Llanelli,  Carmarthenshire; UK-wide fosters)",
    "distance_miles": 150.3,
    "source": "Many Tears",
    "reserved": false,
    "first_seen": "2026-06-02T11:21:15.107752+00:00"
  },
  {
    "url": "https://www.helpinghoundshampshire.com/dog-information/tess",
    "name": "Tess",
    "breed": "Sharpei x collie",
    "age": "11 years",
    "sex": "Female",
    "location": "Helping Hounds (Grayshott, Surrey/Hants)",
    "distance_miles": 25.3,
    "source": "Helping Hounds",
    "reserved": false,
    "first_seen": "2026-06-01T17:11:13.004437+00:00"
  },
  {
    "url": "https://www.spanielassist.com/adopt#enzo",
    "name": "Enzo",
    "breed": "Cocker Spaniel / Working Cocker",
    "age": null,
    "sex": null,
    "location": "Spaniel Assist (UK-wide fosters)",
    "distance_miles": 107.1,
    "source": "Spaniel Assist",
    "reserved": false,
    "first_seen": "2026-05-29T14:51:56.260925+00:00"
  },
  {
    "url": "https://spanielaid.co.uk/spaniel/charlie-sa4746/",
    "name": "Charlie",
    "breed": "Springer Spaniel",
    "age": null,
    "sex": null,
    "location": "Walton on Thames, Surry",
    "distance_miles": null,
    "source": "Spaniel Aid",
    "reserved": true,
    "first_seen": "2026-05-23T20:29:59.469110+00:00"
  },
  {
    "url": "https://www.protectingprelovedbordercollies.org.uk/dogs-for-rehoming#daisy",
    "name": "Daisy",
    "breed": "Border Collie (rescue specialist)",
    "age": "2 years",
    "sex": null,
    "location": "PPBC (Ammanford, Wales; UK-wide fosters)",
    "distance_miles": 147.3,
    "source": "PPBC",
    "reserved": false,
    "first_seen": "2026-05-15T17:11:25.750652+00:00"
  },
  {
    "url": "https://spanielaid.co.uk/spaniel/archer-sa5074/",
    "name": "Archer",
    "breed": "Cocker Cross",
    "age": null,
    "sex": "Male",
    "location": "Epping, Essex",
    "distance_miles": 92.2,
    "source": "Spaniel Aid",
    "reserved": true,
    "first_seen": "2026-05-15T13:03:33.498134+00:00"
  },
  {
    "url": "https://spanielaid.co.uk/spaniel/poppy-sa4571/",
    "name": "Poppy",
    "breed": "Springer spaniel",
    "age": null,
    "sex": "Female",
    "location": "Edinburgh, Scotland",
    "distance_miles": 415.6,
    "source": "Spaniel Aid",
    "reserved": true,
    "first_seen": "2026-05-08T21:12:56.156544+00:00"
  },
  {
    "url": "https://spanielaid.co.uk/spaniel/toby-sa4979/",
    "name": "Toby",
    "breed": "Springer x Clumber x WCS",
    "age": null,
    "sex": "Male",
    "location": "Ipswich, England",
    "distance_miles": null,
    "source": "Spaniel Aid",
    "reserved": true,
    "first_seen": "2026-05-07T12:06:24.124362+00:00"
  },
  {
    "url": "https://spanielaid.co.uk/spaniel/255750/",
    "name": "Benny",
    "breed": "Working Cocker",
    "age": null,
    "sex": "Male",
    "location": "Harlow, Essex, England",
    "distance_miles": 92.2,
    "source": "Spaniel Aid",
    "reserved": true,
    "first_seen": "2026-05-07T07:42:15.018215+00:00"
  },
  {
    "url": "https://spanielaid.co.uk/spaniel/mabel-sa4920-foster-view-to-adopt/",
    "name": "Mabel",
    "breed": "Working cocker spaniel",
    "age": null,
    "sex": "Female",
    "location": "New Forest, Hampshire",
    "distance_miles": 25.2,
    "source": "Spaniel Aid",
    "reserved": true,
    "first_seen": "2026-05-06T15:39:56.868036+00:00"
  },
  {
    "url": "https://spanielaid.co.uk/spaniel/xena-sa4886/",
    "name": "Xena",
    "breed": "Working Cocker Spanial",
    "age": null,
    "sex": "Female",
    "location": "Tonbridge, Kent, England",
    "distance_miles": 75.1,
    "source": "Spaniel Aid",
    "reserved": true,
    "first_seen": "2026-05-06T15:39:56.868036+00:00"
  },
  {
    "url": "https://spanielaid.co.uk/spaniel/256218/",
    "name": "Milo",
    "breed": "New Forest - RESERVED Springer Spaniel",
    "age": null,
    "sex": "Male",
    "location": "New Forest",
    "distance_miles": null,
    "source": "Spaniel Aid",
    "reserved": true,
    "first_seen": "2026-05-06T01:15:23.335704+00:00"
  },
  {
    "url": "https://www.protectingprelovedbordercollies.org.uk/dogs-for-rehoming#shadow",
    "name": "Shadow",
    "breed": "Border Collie (rescue specialist)",
    "age": "15 months",
    "sex": null,
    "location": "PPBC (Ammanford, Wales; UK-wide fosters)",
    "distance_miles": 147.3,
    "source": "PPBC",
    "reserved": false,
    "first_seen": "2026-05-05T16:12:19.976424+00:00"
  },
  {
    "url": "https://spanielaid.co.uk/spaniel/jaycob-sa4688/",
    "name": "Jaycob",
    "breed": "Foster View to Adopt Springer spaniel",
    "age": null,
    "sex": "Male",
    "location": "Highbridge",
    "distance_miles": null,
    "source": "Spaniel Aid",
    "reserved": false,
    "first_seen": "2026-05-05T09:31:34.193242+00:00"
  },
  {
    "url": "https://spanielaid.co.uk/spaniel/bandit-sa4907/",
    "name": "Bandit",
    "breed": "Sprocker",
    "age": null,
    "sex": "Male",
    "location": "Wigan, Greater Manchester, England",
    "distance_miles": 193.8,
    "source": "Spaniel Aid",
    "reserved": true,
    "first_seen": "2026-05-05T09:31:34.193242+00:00"
  },
  {
    "url": "https://spanielaid.co.uk/spaniel/maisie-sa4707/",
    "name": "Maisie",
    "breed": "Foster",
    "age": null,
    "sex": "Female",
    "location": "view to Adopt Springer Spaniel, West Ealing",
    "distance_miles": null,
    "source": "Spaniel Aid",
    "reserved": false,
    "first_seen": "2026-05-05T01:54:32.660488+00:00"
  },
  {
    "url": "https://spanielaid.co.uk/spaniel/alf-sa4540/",
    "name": "Alf",
    "breed": "Cocker spaniel",
    "age": "3 years",
    "sex": "Male",
    "location": "Northampton, England",
    "distance_miles": null,
    "source": "Spaniel Aid",
    "reserved": true,
    "first_seen": "2026-05-05T01:50:42.673174+00:00"
  },
  {
    "url": "https://chilternsdogrescue.org.uk/dog/tibby/",
    "name": "Tibby",
    "breed": "collie",
    "age": "5 months",
    "sex": "Female",
    "location": "Chilterns Dog Rescue (Chalfont St Peter, Bucks)",
    "distance_miles": 59.8,
    "source": "Chilterns Dog Rescue",
    "reserved": false,
    "first_seen": "2026-04-30T13:02:50.643981+00:00"
  },
  {
    "url": "https://www.secondchanceanimalrescue.co.uk/2026/04/27/lola/",
    "name": "Lola",
    "breed": "Collie/Springer match",
    "age": "11 month",
    "sex": null,
    "location": "Second Chance Animal Rescue (Southampton)",
    "distance_miles": 20.4,
    "source": "Second Chance Animal Rescue",
    "reserved": false,
    "first_seen": null
  },
  {
    "url": "https://www.secondchanceanimalrescue.co.uk/2025/01/12/saint/",
    "name": "Saint",
    "breed": "Collie/Springer match",
    "age": "11 months",
    "sex": null,
    "location": "Second Chance Animal Rescue (Southampton)",
    "distance_miles": 20.4,
    "source": "Second Chance Animal Rescue",
    "reserved": false,
    "first_seen": null
  },
  {
    "url": "https://www.helpinghoundshampshire.com/dog-information/chloe",
    "name": "Chloe",
    "breed": "Kokoni X Spaniel",
    "age": "14 months",
    "sex": "Female",
    "location": "Helping Hounds (Grayshott, Surrey/Hants)",
    "distance_miles": 25.3,
    "source": "Helping Hounds",
    "reserved": false,
    "first_seen": null
  },
  {
    "url": "https://www.dogstrust.org.uk/rehoming/dogs/collie-border/3566626",
    "name": "Trilby",
    "breed": "Collie (Border) Cross",
    "age": "4y 8m",
    "sex": "Male",
    "location": "Dogs Trust Shoreham (Sussex)",
    "distance_miles": 31.3,
    "source": "Dogs Trust",
    "reserved": false,
    "first_seen": null
  },
  {
    "url": "https://www.arundawndogrescue.co.uk/bigwins",
    "name": "Bigwins",
    "breed": "Collie/Springer match",
    "age": "15 months",
    "sex": null,
    "location": "Arundawn Dog Rescue (Horsham, West Sussex)",
    "distance_miles": 34.7,
    "source": "Arundawn",
    "reserved": false,
    "first_seen": null
  },
  {
    "url": "https://www.dogstrust.org.uk/rehoming/dogs/spaniel-english-springer/3470953",
    "name": "Andy Pandy Pudding and Pie",
    "breed": "Spaniel (English Springer)",
    "age": "3y 10m",
    "sex": "Male",
    "location": "Dogs Trust Salisbury (Wiltshire)",
    "distance_miles": 40.5,
    "source": "Dogs Trust",
    "reserved": false,
    "first_seen": null
  },
  {
    "url": "https://www.dogstrust.org.uk/rehoming/dogs/akita/3621821",
    "name": "Hugo",
    "breed": "Akita Cross \u00d7 Collie (Border)",
    "age": "1y 8m",
    "sex": "Male",
    "location": "Dogs Trust Newbury (Berkshire)",
    "distance_miles": 45.3,
    "source": "Dogs Trust",
    "reserved": false,
    "first_seen": null
  },
  {
    "url": "https://www.lastchanceanimalrescue.co.uk/kennel/dog.php#Dancer",
    "name": "Dancer",
    "breed": "Collie x",
    "age": "9yrs",
    "sex": "Male",
    "location": "Last Chance Edenbridge",
    "distance_miles": 53.5,
    "source": "Last Chance",
    "reserved": false,
    "first_seen": null
  },
  {
    "url": "https://www.lastchanceanimalrescue.co.uk/kennel/dog.php#Gunner",
    "name": "Gunner",
    "breed": "Spaniel",
    "age": "7yrs",
    "sex": "Male",
    "location": "Last Chance Edenbridge",
    "distance_miles": 53.5,
    "source": "Last Chance",
    "reserved": false,
    "first_seen": null
  },
  {
    "url": "https://mikeysdogrescue.co.uk/pages/adopt-a-dog",
    "name": "Freddie",
    "breed": "KC Registered American Show Cocker",
    "age": "7 Years Old",
    "sex": "Male",
    "location": "Mikey's Dog Rescue (Dorset)",
    "distance_miles": 63.4,
    "source": "Mikey's Dog Rescue",
    "reserved": false,
    "first_seen": null
  },
  {
    "url": "https://www.ferneanimalsanctuary.org/animal/ozzy/",
    "name": "Ozzy",
    "breed": "Collie/Springer match",
    "age": null,
    "sex": "Male",
    "location": "Ferne Animal Sanctuary (Chard, Somerset)",
    "distance_miles": 86.4,
    "source": "Ferne",
    "reserved": false,
    "first_seen": null
  },
  {
    "url": "https://heathlands.org.uk/dog.php?id=744",
    "name": "Penn",
    "breed": "Border Collie cross",
    "age": "5yrs",
    "sex": null,
    "location": "Heathlands Animal Sanctuary (Royston, Herts)",
    "distance_miles": 96.9,
    "source": "Heathlands Animal Sanctuary",
    "reserved": false,
    "first_seen": null
  },
  {
    "url": "https://www.saveourspaniels.org.uk/dogs-needing-homes",
    "name": "Triana",
    "breed": "Breton / Spaniel mix",
    "age": "6",
    "sex": null,
    "location": "Save Our Spaniels (Peterborough, Cambridgeshire; UK-wide fosters)",
    "distance_miles": 107.1,
    "source": "Save Our Spaniels",
    "reserved": false,
    "first_seen": null
  },
  {
    "url": "https://www.spanielassist.com/adopt#arlo",
    "name": "Arlo",
    "breed": "Cocker Spaniel / Working Cocker",
    "age": null,
    "sex": null,
    "location": "Spaniel Assist (UK-wide fosters)",
    "distance_miles": 107.1,
    "source": "Spaniel Assist",
    "reserved": false,
    "first_seen": null
  },
  {
    "url": "https://www.spanielassist.com/adopt#ollie",
    "name": "Ollie",
    "breed": "Cocker Spaniel / Working Cocker",
    "age": null,
    "sex": null,
    "location": "Spaniel Assist (UK-wide fosters)",
    "distance_miles": 107.1,
    "source": "Spaniel Assist",
    "reserved": false,
    "first_seen": null
  },
  {
    "url": "https://www.spanielassist.com/adopt#winnie",
    "name": "Winnie",
    "breed": "Cocker Spaniel / Working Cocker",
    "age": null,
    "sex": null,
    "location": "Spaniel Assist (UK-wide fosters)",
    "distance_miles": 107.1,
    "source": "Spaniel Assist",
    "reserved": false,
    "first_seen": null
  },
  {
    "url": "https://www.protectingprelovedbordercollies.org.uk/dogs-for-rehoming#buddy",
    "name": "Buddy",
    "breed": "Border Collie (rescue specialist)",
    "age": "2 years",
    "sex": null,
    "location": "PPBC (Ammanford, Wales; UK-wide fosters)",
    "distance_miles": 147.3,
    "source": "PPBC",
    "reserved": false,
    "first_seen": null
  },
  {
    "url": "https://www.protectingprelovedbordercollies.org.uk/dogs-for-rehoming#nia",
    "name": "Nia",
    "breed": "Border Collie (rescue specialist)",
    "age": "8 months",
    "sex": null,
    "location": "PPBC (Ammanford, Wales; UK-wide fosters)",
    "distance_miles": 147.3,
    "source": "PPBC",
    "reserved": false,
    "first_seen": null
  },
  {
    "url": "https://www.protectingprelovedbordercollies.org.uk/dogs-for-rehoming#seth",
    "name": "SETH",
    "breed": "Border Collie (rescue specialist)",
    "age": "2 years",
    "sex": null,
    "location": "PPBC (Ammanford, Wales; UK-wide fosters)",
    "distance_miles": 147.3,
    "source": "PPBC",
    "reserved": false,
    "first_seen": null
  },
  {
    "url": "https://www.manytearsrescue.org/adopt/dogs/5749/",
    "name": "Clippa",
    "breed": "Springer Spaniel",
    "age": "9 years",
    "sex": "Female",
    "location": "Many Tears (In Foster: Fernhurst,  West Sussex; UK-wide fosters)",
    "distance_miles": 150.3,
    "source": "Many Tears",
    "reserved": false,
    "first_seen": null
  },
  {
    "url": "https://www.manytearsrescue.org/adopt/dogs/1745/",
    "name": "Emrys",
    "breed": "Collie",
    "age": "4 years",
    "sex": "Male",
    "location": "Many Tears (In Foster: Morriston,  Swansea; UK-wide fosters)",
    "distance_miles": 150.3,
    "source": "Many Tears",
    "reserved": false,
    "first_seen": null
  },
  {
    "url": "https://www.manytearsrescue.org/adopt/dogs/2709/",
    "name": "Gabriel",
    "breed": "Beagle x Cocker Spaniel",
    "age": "4 years",
    "sex": "Male",
    "location": "Many Tears (Many Tears,  Llanelli,  Carmarthenshire; UK-wide fosters)",
    "distance_miles": 150.3,
    "source": "Many Tears",
    "reserved": false,
    "first_seen": null
  },
  {
    "url": "https://www.manytearsrescue.org/adopt/dogs/5746/",
    "name": "Jerry",
    "breed": "Collie",
    "age": "3 years",
    "sex": "Male",
    "location": "Many Tears (Many Tears,  Llanelli,  Carmarthenshire; UK-wide fosters)",
    "distance_miles": 150.3,
    "source": "Many Tears",
    "reserved": false,
    "first_seen": null
  },
  {
    "url": "https://www.manytearsrescue.org/adopt/dogs/4962/",
    "name": "Lassie",
    "breed": "Collie",
    "age": "2 years",
    "sex": "Female",
    "location": "Many Tears (Many Tears,  Llanelli,  Carmarthenshire; UK-wide fosters)",
    "distance_miles": 150.3,
    "source": "Many Tears",
    "reserved": false,
    "first_seen": null
  },
  {
    "url": "https://www.manytearsrescue.org/adopt/dogs/1671/",
    "name": "Margate",
    "breed": "Beagle x Cocker Spaniel",
    "age": "5 years",
    "sex": "Male",
    "location": "Many Tears (Many Tears,  Llanelli,  Carmarthenshire; UK-wide fosters)",
    "distance_miles": 150.3,
    "source": "Many Tears",
    "reserved": false,
    "first_seen": null
  },
  {
    "url": "https://www.manytearsrescue.org/adopt/dogs/2656/",
    "name": "Toby",
    "breed": "Cocker Spaniel",
    "age": "6 years",
    "sex": "Male",
    "location": "Many Tears (Many Tears,  Llanelli,  Carmarthenshire; UK-wide fosters)",
    "distance_miles": 150.3,
    "source": "Many Tears",
    "reserved": false,
    "first_seen": null
  },
  {
    "url": "https://www.manytearsrescue.org/adopt/dogs/5322/",
    "name": "Toucan",
    "breed": "Collie",
    "age": "6 years",
    "sex": "Male",
    "location": "Many Tears (Many Tears,  Llanelli,  Carmarthenshire; UK-wide fosters)",
    "distance_miles": 150.3,
    "source": "Many Tears",
    "reserved": false,
    "first_seen": null
  },
  {
    "url": "https://www.manytearsrescue.org/adopt/dogs/5659/",
    "name": "Trixie",
    "breed": "Cocker Spaniel",
    "age": "5 years",
    "sex": "Female",
    "location": "Many Tears (Many Tears,  Llanelli,  Carmarthenshire; UK-wide fosters)",
    "distance_miles": 150.3,
    "source": "Many Tears",
    "reserved": false,
    "first_seen": null
  },
  {
    "url": "https://www.dogsblog.com/bilbo-29/",
    "name": "Bilbo",
    "breed": "Spaniel Cross",
    "age": "3-5 years",
    "sex": "Male",
    "location": "South East England",
    "distance_miles": null,
    "source": "Dogsblog",
    "reserved": false,
    "first_seen": null
  },
  {
    "url": "https://www.dogstrust.org.uk/rehoming/dogs/collie-border/1199838",
    "name": "Alfie",
    "breed": "Collie (Border) Cross",
    "age": "8y 5m",
    "sex": "Male",
    "location": "Dogs Trust Shoreham (Sussex)",
    "distance_miles": 31.3,
    "source": "Dogs Trust",
    "reserved": true,
    "first_seen": null
  },
  {
    "url": "https://spanielaid.co.uk/spaniel/charlie-sa4938/",
    "name": "Charlie",
    "breed": "English Springer Spaniel",
    "age": null,
    "sex": "Male",
    "location": "London, N10",
    "distance_miles": 62.7,
    "source": "Spaniel Aid",
    "reserved": true,
    "first_seen": null
  },
  {
    "url": "https://mikeysdogrescue.co.uk/pages/adopt-a-dog-page-2-of-2",
    "name": "Ramsey",
    "breed": "Cocker Spaniel",
    "age": "4 1/2 Years Old",
    "sex": "Male",
    "location": "Mikey's Dog Rescue (Dorset)",
    "distance_miles": 63.4,
    "source": "Mikey's Dog Rescue",
    "reserved": true,
    "first_seen": null
  },
  {
    "url": "https://spanielaid.co.uk/spaniel/indi-sa5437/",
    "name": "Indi",
    "breed": "English Springer Spaniel",
    "age": "5 years",
    "sex": "Female",
    "location": "Ware, SG12",
    "distance_miles": 84.3,
    "source": "Spaniel Aid",
    "reserved": true,
    "first_seen": null
  },
  {
    "url": "https://spanielaid.co.uk/spaniel/maggie-sa4817-skye-sa4818/",
    "name": "Maggie",
    "breed": "& SKYE SA4818 - RESERVED Springer Spaniels",
    "age": null,
    "sex": "Female",
    "location": "Epping, Essex",
    "distance_miles": 92.2,
    "source": "Spaniel Aid",
    "reserved": true,
    "first_seen": null
  },
  {
    "url": "https://spanielaid.co.uk/spaniel/ben-sa4687/",
    "name": "Ben",
    "breed": "Springer spaniel",
    "age": null,
    "sex": "Male",
    "location": "Stockport, England",
    "distance_miles": null,
    "source": "Spaniel Aid",
    "reserved": true,
    "first_seen": null
  },
  {
    "url": "https://spanielaid.co.uk/spaniel/percy-sa5099/",
    "name": "Percy",
    "breed": "- Spaniel Aid CIO",
    "age": null,
    "sex": "Male",
    "location": "Spaniel Aid foster (UK)",
    "distance_miles": null,
    "source": "Spaniel Aid",
    "reserved": true,
    "first_seen": null
  },
  {
    "url": "https://agilitynet.co.uk/activepages/rescues.asp#rex",
    "name": "Rex",
    "breed": "Border Collie",
    "age": "1 1/2 years",
    "sex": "Dog",
    "location": "Wethersfield, Essex CM7 4EP",
    "distance_miles": 92.2,
    "source": "AgilityNet",
    "reserved": false,
    "first_seen": null
  },
  {
    "url": "https://www.englishspringerrescue.co.uk/charlie-9/",
    "name": "Charlie",
    "breed": "English Springer Spaniel",
    "age": null,
    "sex": null,
    "location": "NWESSR (North West England)",
    "distance_miles": 183.0,
    "source": "NWESSR",
    "reserved": false,
    "first_seen": null
  },
  {
    "url": "https://www.syessr.org.uk/items/boy-puppy-%231",
    "name": "Boy Puppy 1",
    "breed": "Springer Spaniel Cross",
    "age": "8 months",
    "sex": null,
    "location": "SYESSR (Sheffield, South Yorkshire)",
    "distance_miles": 219.6,
    "source": "SYESSR",
    "reserved": false,
    "first_seen": null
  },
  {
    "url": "https://www.syessr.org.uk/items/boy-puppy-%234",
    "name": "Boy Puppy 4",
    "breed": "Springer Spaniel Cross",
    "age": "8 months",
    "sex": null,
    "location": "SYESSR (Sheffield, South Yorkshire)",
    "distance_miles": 219.6,
    "source": "SYESSR",
    "reserved": false,
    "first_seen": null
  },
  {
    "url": "https://www.syessr.org.uk/items/boy-puppy%232",
    "name": "Boy Puppy2",
    "breed": "Springer Spaniel Cross",
    "age": "8 months",
    "sex": null,
    "location": "SYESSR (Sheffield, South Yorkshire)",
    "distance_miles": 219.6,
    "source": "SYESSR",
    "reserved": false,
    "first_seen": null
  },
  {
    "url": "https://www.syessr.org.uk/items/charlie",
    "name": "Charlie",
    "breed": "Cocker Spaniel",
    "age": "08/09/18",
    "sex": "Male",
    "location": "SYESSR (Sheffield, South Yorkshire)",
    "distance_miles": 219.6,
    "source": "SYESSR",
    "reserved": false,
    "first_seen": null
  },
  {
    "url": "https://www.syessr.org.uk/items/girl-puppy-%231",
    "name": "Girl Puppy 1",
    "breed": "Springer Spaniel Cross",
    "age": "8 months",
    "sex": null,
    "location": "SYESSR (Sheffield, South Yorkshire)",
    "distance_miles": 219.6,
    "source": "SYESSR",
    "reserved": false,
    "first_seen": null
  },
  {
    "url": "https://www.syessr.org.uk/items/leo",
    "name": "Leo",
    "breed": "Cocker Spaniel",
    "age": "6y 6m",
    "sex": "Male",
    "location": "SYESSR (Sheffield, South Yorkshire)",
    "distance_miles": 219.6,
    "source": "SYESSR",
    "reserved": false,
    "first_seen": null
  },
  {
    "url": "https://www.syessr.org.uk/items/milo",
    "name": "Milo",
    "breed": "Cocker Spaniel",
    "age": "6y 6m",
    "sex": "Male",
    "location": "SYESSR (Sheffield, South Yorkshire)",
    "distance_miles": 219.6,
    "source": "SYESSR",
    "reserved": false,
    "first_seen": null
  },
  {
    "url": "https://www.syessr.org.uk/items/toby",
    "name": "Toby",
    "breed": "Springer Spaniel",
    "age": "11y 9m",
    "sex": "Male",
    "location": "SYESSR (Sheffield, South Yorkshire)",
    "distance_miles": 219.6,
    "source": "SYESSR",
    "reserved": false,
    "first_seen": null
  },
  {
    "url": "https://www.dogsblog.com/elsa-75/",
    "name": "Elsa",
    "breed": "Spaniel Cross",
    "age": null,
    "sex": null,
    "location": "Location not tagged",
    "distance_miles": null,
    "source": "Dogsblog",
    "reserved": false,
    "first_seen": null
  },
  {
    "url": "https://www.dogsblog.com/ernesto-2/",
    "name": "Ernesto",
    "breed": "Collie Cross",
    "age": "3-5 years",
    "sex": "Male",
    "location": "Location not tagged",
    "distance_miles": null,
    "source": "Dogsblog",
    "reserved": false,
    "first_seen": null
  },
  {
    "url": "https://www.dogsblog.com/folti-2/",
    "name": "Folti",
    "breed": "Border Collie Cross",
    "age": "3-5 years",
    "sex": "Male",
    "location": "Location not tagged",
    "distance_miles": null,
    "source": "Dogsblog",
    "reserved": false,
    "first_seen": null
  },
  {
    "url": "https://www.dogsblog.com/reyna-4/",
    "name": "Reyna",
    "breed": "Border Collie",
    "age": "6+ years",
    "sex": "Female",
    "location": "Location not tagged",
    "distance_miles": null,
    "source": "Dogsblog",
    "reserved": false,
    "first_seen": null
  },
  {
    "url": "https://www.dogsblog.com/sherlock-26/",
    "name": "Sherlock",
    "breed": "Spaniel Cross",
    "age": null,
    "sex": null,
    "location": "Location not tagged",
    "distance_miles": null,
    "source": "Dogsblog",
    "reserved": false,
    "first_seen": null
  },
  {
    "url": "https://www.dogsblog.com/syd-7/",
    "name": "Syd",
    "breed": "Cocker Spaniel Cross",
    "age": null,
    "sex": null,
    "location": "Location not tagged",
    "distance_miles": null,
    "source": "Dogsblog",
    "reserved": false,
    "first_seen": null
  },
  {
    "url": "https://spanielaid.co.uk/spaniel/mila-sa4409-2/",
    "name": "Mila",
    "breed": "Honorary spaniel",
    "age": null,
    "sex": "Female",
    "location": "Ashbourne, Derbyshire, England",
    "distance_miles": 161.1,
    "source": "Spaniel Aid",
    "reserved": true,
    "first_seen": null
  }
]